{
  "title": "Get Users",
  "type": "object",
  "properties": {
    "Issuer": {
      "type": "boolean",
      "sanitize": "mongo"
    },
    "SiteID": {
      "$ref": "common.json#/definitions/ids"
    },
    "UserID": {
      "$ref": "common.json#/definitions/ids"
    },
    "Role": {
      "type": "string",
      "sanitize": "mongo",
      "pattern": "^[SABD](\\|[SABD])*$"
    },
    "Technical": {
      "type": "boolean",
      "sanitize": "mongo"
    },
    "FreeAccess": {
      "type": "boolean",
      "sanitize": "mongo"
    },
    "Status": {
      "type": "string",
      "sanitize": "mongo",
      "pattern": "^[PAIBL](\\|[PAIBL])*$"
    },
    "ExcludeSiteID": {
      "$ref": "common.json#/definitions/ids"
    },
    "VisualTagID": {
      "type": "string",
      "sanitize": "mongo"
    },
    "Search": {
      "$ref": "common.json#/definitions/search"
    },
    "SortFields": {
      "$ref": "common.json#/definitions/sortFields"
    },
    "Limit": {
      "$ref": "common.json#/definitions/limit"
    },
    "Skip": {
      "$ref": "common.json#/definitions/skip"
    },
    "OnlyRecordCount": {
      "$ref": "common.json#/definitions/onlyRecordCount"
    },
    "ProjectFields": {
      "$ref": "common.json#/definitions/projectFields"
    }
  },
  "required": [
    "Limit"
  ]
}
