{
  "subject": "Restablecer contraseña",
  "tenant": "",
  "baseURL": "<%- evseDashboardURL %>",
  "body": {
    "header": {
      "title": "Restablecer contraseña",
      "image": {
        "left": {
          "height": 60,
          "url": "<%- evseDashboardURL %>/assets/img/logo-email.gif"
        },
        "right": {
          "height": 50,
          "url": "<%- evseDashboardURL %>/assets/img/info.png"
        }
      }
    },
    "beforeActionLines": [
      "Hola <%- (user.firstName?user.firstName:user.name) %>,",
      "",
      "Acaba de solicitar una contraseña nueva.",
      "",
      "Haga click en el enlace para generar y recibir una constraseña nueva."
    ],
    "actions": [{
      "title": "Restablecer contraseña",
      "url": "<%- evseDashboardResetPassURL %>"
    }],
    "afterActionLines": [
      "Si no ha solicitado reestablecer su contraseña, puede ignorar este correo.",
      "",
      "Atentamente,",
      "EV Admins."
    ],
    "footer": {
    }
  }
}
