{
  "subject": "Compte de facturation activé",
  "tenant": "<%- tenantID %>",
  "baseURL": "<%- evseDashboardURL %>",
  "body": {
    "header": {
      "title": "Compte de facturation activé",
      "image": {
        "left": {
          "height": 60,
          "url": "<%- tenantLogoURL %>"
        },
        "right": {
          "height": 50,
          "url": "<%- evseDashboardURL %>/assets/img/info.png"
        }
      }
    },
    "beforeActionLines": [
      "Dear <%- (user.firstName ? user.firstName : user.name) %>,",
      "",
      "Votre compte de facturation a été activé."
    ],
    "afterActionLines": [
      "Cordialement,",
      "EV Admins."
    ],
    "footer": {
    }
  }
}
