{
  "subject": "Session Not Started",
  "tenant": "",
  "baseURL": "<%- evseDashboardURL %>",
  "body": {
    "header": {
      "title": "Session Not Started",
      "image": {
        "left": {
          "height": 60,
          "url": "<%- evseDashboardURL %>/assets/img/logo-email.gif"
        },
        "right": {
          "height": 50,
          "url": "<%- evseDashboardURL %>/assets/img/info.png"
        }
      }
    },
    "beforeActionLines": [
      "Dear User,",
      "",
      "You haven't started the session of your vehicle on charging station <b>'<%- chargingStation %>'</b>.",
      ""
    ],
    "afterActionLines": [
      "Best Regards,",
      "EV Admins."
    ],
    "footer": {
    }
  }
}

