{
  "subject": "<%- chargeBoxID %> s'est enregistrée",
  "baseURL": "<%- evseDashboardURL %>",
  "body": {
    "header": {
      "title": "Borne Enregistrée",
      "image": {
        "left": {
          "height": 60,
          "url": "<%- evseDashboardURL %>/assets/img/logo-email.gif"
        },
        "right": {
          "height": 50,
          "url": "<%- evseDashboardURL %>/assets/img/info.png"
        }
      }
    },
    "beforeActionLines": [
      "Bonjour Admin,",
      "",
      "<b><%- chargeBoxID %></b> vient de s'enregistrer sur le serveur central."
    ],
    "action": {
      "title": "Voir <%- chargeBoxID %>",
      "url": "<%- evseDashboardChargingStationURL %>"
    },
    "afterActionLines": [
      "Cordialement,",
      "EV Admins."
    ],
    "footer": {
    }
  }
}
