{
  "subject": "Utilisateur inconnu",
  "tenant": "",
  "baseURL": "<%- evseDashboardURL %>",
  "body": {
    "header": {
      "title": "Utilisateur Inconnu",
      "image": {
        "left": {
          "height": 60,
          "url": "<%- evseDashboardURL %>/assets/img/logo-email.gif"
        },
        "right": {
          "height": 50,
          "url": "<%- evseDashboardURL %>/assets/img/info.png"
        }
      }
    },
    "beforeActionLines": [
      "Bonjour Admin,",
      "",
      "Un utilisateur inconnu vient juste de badger sur <b><%- chargeBoxID %></b> avec le badge ID <b><%- badgeId %></b>."
    ],
    "action": {
      "title": "Editer Utilisateur",
      "url": "<%- evseDashboardUserURL %>"
    },
    "afterActionLines": [
      "Cordialement,",
      "EV Admins."
    ],
    "footer": {
    }
  }
}
