[
  {
    "id": "A",
    "name": "Admin",
    "auths": [
      {
        "AuthObject": "User",
        "AuthFieldValue": {
          "UserID": "*",
          "Action": ["Create","Update","Read","Delete"]
        }
      },
      {
        "AuthObject": "ChargingStation",
        "AuthFieldValue": {
          "Action": ["Read", "Reset", "ClearCache", "GetConfiguration", "StopTransaction", "UnlockConnector"]
        }
      },
      {
        "AuthObject": "Logging",
        "AuthFieldValue": {
          "Action": ["Read"]
        }
      }
    ]
  },
  {
    "id": "B",
    "name": "Basic",
    "auths": [
      {
        "AuthObject": "User",
        "AuthFieldValue": {
          "UserID": ["{{user.id}}"],
          "Action": ["Update","Read"]
        }
      },
      {
        "AuthObject": "ChargingStation",
        "AuthFieldValue": {
          "Action": []
        }
      },
      {
        "AuthObject": "Logging",
        "AuthFieldValue": {
          "Action": []
        }
      }
    ]
  }
]
